demquery/__init__.py
demquery/demquery.py
demquery-0.1.0.dist-info/LICENSE
demquery-0.1.0.dist-info/METADATA
demquery-0.1.0.dist-info/WHEEL
demquery-0.1.0.dist-info/top_level.txt
demquery-0.1.0.dist-info/RECORD
