Metadata-Version: 2.1
Name: demquery
Version: 0.1.0
Summary: Wrapper around rasterio to query points on a Digital Elevation Model
Home-page: https://github.com/kylebarron/demquery
Author: Kyle Barron
Author-email: kylebarron2@gmail.com
License: MIT license
Keywords: demquery
Platform: UNKNOWN
Classifier: Development Status :: 3 - Alpha
Classifier: Intended Audience :: Developers
Classifier: License :: OSI Approved :: MIT License
Classifier: Natural Language :: English
Classifier: Programming Language :: Python :: 3
Classifier: Programming Language :: Python :: 3.5
Classifier: Programming Language :: Python :: 3.6
Classifier: Programming Language :: Python :: 3.7
Classifier: Programming Language :: Python :: 3.8
Requires-Python: >=3.5
Requires-Dist: numpy (>=1.16)
Requires-Dist: rasterio (>=1.0)
Requires-Dist: scipy (>=1.0.0)
